rest_framework_money_field/__init__.py
rest_framework_money_field/py.typed
rest_framework_money_field-2.2.1.dist-info/LICENSE
rest_framework_money_field-2.2.1.dist-info/METADATA
rest_framework_money_field-2.2.1.dist-info/WHEEL
rest_framework_money_field-2.2.1.dist-info/RECORD
