Metadata-Version: 2.1
Name: rest-framework-money-field
Version: 2.2.1
Summary: A DRF serializer for monetary values.
License: MIT
Author: Rauli Laine
Author-email: rauli.laine@treet.fi
Requires-Python: >=3.8.1,<4.0
Classifier: License :: OSI Approved :: MIT License
Classifier: Programming Language :: Python :: 3
Classifier: Programming Language :: Python :: 3.9
Classifier: Programming Language :: Python :: 3.10
Classifier: Programming Language :: Python :: 3.11
Classifier: Programming Language :: Python :: 3.12
Classifier: Programming Language :: Python :: 3.13
Requires-Dist: djangorestframework (>3.7.0,<4.0.0)
Requires-Dist: py-moneyed (>=2.0,<3.0)
